{
  "parent": "minecraft:recipes/root",
  "rewards": {
    "recipes": [
      "stairs:stairs_magma"
    ]
  },
  "criteria": {
    "has_magma": {
      "trigger": "minecraft:inventory_changed",
      "conditions": {
        "items": [
          {
            "item": "minecraft:magma"
          }
        ]
      }
    },
    "has_the_recipe": {
      "trigger": "minecraft:recipe_unlocked",
      "conditions": {
        "recipe": "stairs:stairs_magma"
      }
    }
  },
  "requirements": [
    [
      "has_magma",
      "has_the_recipe"
    ]
  ]
}
